biopytorch/__init__.py
biopytorch/bioconv2d.py
biopytorch/biolinear.py
biopytorch/biotrainer.py
biopytorch-0.0.1.dist-info/LICENSE
biopytorch-0.0.1.dist-info/METADATA
biopytorch-0.0.1.dist-info/WHEEL
biopytorch-0.0.1.dist-info/top_level.txt
biopytorch-0.0.1.dist-info/RECORD
