Metadata-Version: 2.1
Name: biopytorch
Version: 0.0.1
Summary: PyTorch implementation of Hebbian "Bio-Learning" convolutional layers
Home-page: https://github.com/Einlar/biopytorch
Author: Francesco Manzali
Author-email: manzali.francesco97@gmail.com
License: UNKNOWN
Project-URL: BugTracker, https://github.com/Einlar/biopytorch/issues
Platform: UNKNOWN
Classifier: Programming Language :: Python :: 3
Classifier: License :: OSI Approved :: MIT License
Classifier: Operating System :: OS Independent
License-File: LICENSE
Requires-Dist: torch (>=1.8)
Requires-Dist: numpy
Requires-Dist: tqdm
Requires-Dist: matplotlib
Requires-Dist: pytorch-lightning
Requires-Dist: optuna
Requires-Dist: wandb ; python_version >= "3.7"
